[
  {
    "id": "w1",
    "title": "Push Day",
    "description": "Peito, ombros e tríceps",
    "type": "Força",
    "exercises": [
      {
        "id": "e1",
        "name": "Supino Plano",
        "description": "Exercício composto para peito",
        "targetMuscle": "Peito",
        "sets": [
          { "id": "s1", "targetType": "WEIGHT", "reps": 10, "weightKg": 60.0, "durationSeconds": 0 },
          { "id": "s2", "targetType": "WEIGHT", "reps": 8,  "weightKg": 70.0, "durationSeconds": 0 },
          { "id": "s3", "targetType": "WEIGHT", "reps": 6,  "weightKg": 80.0, "durationSeconds": 0 }
        ],
        "machineConfigs": []
      },
      {
        "id": "e2",
        "name": "Press Militar",
        "description": "Exercício composto para ombros",
        "targetMuscle": "Ombros",
        "sets": [
          { "id": "s4", "targetType": "WEIGHT", "reps": 10, "weightKg": 40.0, "durationSeconds": 0 },
          { "id": "s5", "targetType": "WEIGHT", "reps": 8,  "weightKg": 45.0, "durationSeconds": 0 }
        ],
        "machineConfigs": []
      }
    ]
  },
  {
    "id": "w2",
    "title": "Pull Day",
    "description": "Costas e bíceps",
    "type": "Força",
    "exercises": [
      {
        "id": "e3",
        "name": "Remada Curvada",
        "description": "Exercício composto para costas",
        "targetMuscle": "Costas",
        "sets": [
          { "id": "s6", "targetType": "WEIGHT", "reps": 10, "weightKg": 60.0, "durationSeconds": 0 },
          { "id": "s7", "targetType": "WEIGHT", "reps": 8,  "weightKg": 70.0, "durationSeconds": 0 }
        ],
        "machineConfigs": []
      }
    ]
  },
  {
    "id": "w3",
    "title": "Core & Cardio",
    "description": "Abdominais e resistência",
    "type": "Resistência",
    "exercises": [
      {
        "id": "e4",
        "name": "Prancha",
        "description": "Isométrico para core",
        "targetMuscle": "Core",
        "sets": [
          { "id": "s8", "targetType": "TIME", "reps": 0, "weightKg": 0.0, "durationSeconds": 60 },
          { "id": "s9", "targetType": "TIME", "reps": 0, "weightKg": 0.0, "durationSeconds": 60 }
        ],
        "machineConfigs": []
      }
    ]
  }
]

